.DS_Store
.gitignore
MANIFEST.in
README.md
setup.py
webdeployer-config.py
bin/webdeployer
generators/__init__.py
generators/gunicorn.tpl
generators/nginx.tpl
generators/project-config.tpl
generators/supervisord.tpl
webdeployer/__init__.py
webdeployer/deployer.py
webdeployer/generator.py
webdeployer.egg-info/PKG-INFO
webdeployer.egg-info/SOURCES.txt
webdeployer.egg-info/dependency_links.txt
webdeployer.egg-info/requires.txt
webdeployer.egg-info/top_level.txt