Metadata-Version: 1.1
Name: webdeployer
Version: 0.0.4
Summary: Personal Deployer for site created with Flask and Django
Home-page: https://github.com/royendgel
Author: Royendgel Silberie
Author-email: royendgel@techprocur.com
License: UNKNOWN
Keywords: deployer automation fabric
Platform: UNKNOWN
Classifier: Operating System :: MacOS :: MacOS X
Classifier: Operating System :: Unix
Classifier: Development Status :: 3 - Alpha
Classifier: Topic :: Utilities
Classifier: Programming Language :: Python :: 2.7
